jqviz/__init__.py
jqviz/jqviz.py
jqviz/templates/index.html
jqviz-0.0.3.dist-info/LICENSE
jqviz-0.0.3.dist-info/METADATA
jqviz-0.0.3.dist-info/WHEEL
jqviz-0.0.3.dist-info/entry_points.txt
jqviz-0.0.3.dist-info/top_level.txt
jqviz-0.0.3.dist-info/RECORD
