Metadata-Version: 2.1
Name: jqviz
Version: 0.0.3
Summary: Visualize your jq commands
Home-page: https://github.com/jkubicek/jqviz
Author: Jim Kubicek
Author-email: jim@jimkubicek.com
Maintainer: Jim Kubicek
Maintainer-email: jim@jimkubicek.com
License: MIT
Platform: UNKNOWN
Classifier: Development Status :: 3 - Alpha
Classifier: Intended Audience :: Developers
Classifier: Programming Language :: Python
Classifier: Programming Language :: Python :: 3.7
Classifier: Programming Language :: Python :: 3.8
Requires-Dist: click
Requires-Dist: Flask
